limco.py
limco-2.0.0.dist-info/entry_points.txt
limco-2.0.0.dist-info/WHEEL
limco-2.0.0.dist-info/METADATA
limco-2.0.0.dist-info/RECORD
