Metadata-Version: 2.1
Name: limco
Version: 2.0.0
Summary: Linguistic Measure Collection
Home-page: https://github.com/sociocom/limco
License: MIT
Author: Shuntaro Yada
Author-email: contact@shuntaroy.com
Requires-Python: >=3.9,<4.0
Classifier: License :: OSI Approved :: MIT License
Classifier: Natural Language :: Japanese
Classifier: Programming Language :: Python :: 3
Classifier: Programming Language :: Python :: 3.9
Classifier: Programming Language :: Python :: 3.10
Classifier: Programming Language :: Python :: 3.11
Classifier: Topic :: Text Processing :: Linguistic
Requires-Dist: fire (>=0.5.0,<0.6.0)
Requires-Dist: ginza (>=5.1.2,<6.0.0)
Requires-Dist: ja-ginza (>=5.1.2,<6.0.0)
Requires-Dist: jaconv (>=0.3.4,<0.4.0)
Requires-Dist: numpy (>=1.24.2,<2.0.0)
Requires-Dist: pandas (>=1.5.3,<2.0.0)
